kmtest/__init__.py
kmtest/helpers.py
kmtest/km_tests.py
kmtest/my_test.py
kmtest/results.py
kmtest/test_kmtest.py
kmtest/test_suite.py
kmtest/validate_fixes.py
kmtest-1.0.1.dist-info/licenses/LICENSE
kmtest-1.0.1.dist-info/METADATA
kmtest-1.0.1.dist-info/WHEEL
kmtest-1.0.1.dist-info/top_level.txt
kmtest-1.0.1.dist-info/RECORD
